[
  {
    "id": 1042,
    "fecha": "24 mayo 2026",
    "estado": "Entregado",
    "id_transaccion": "TXN-8A3F2C1D",
    "total": "329.980",
    "cliente": "María González",
    "items": [
      {
        "nombre": "Cuna Clásica",
        "cantidad": 1,
        "precio": "129.990",
        "imagen": "peque-mueble.webp"
      },
      {
        "nombre": "Cómoda 3 Cajones",
        "cantidad": 2,
        "precio": "199.980",
        "imagen": "peque-mueble.webp"
      }
    ]
  },
  {
    "id": 1041,
    "fecha": "10 mayo 2026",
    "estado": "Pendiente",
    "id_transaccion": "TXN-5E9B4A7C",
    "total": "89.990",
    "cliente": "María González",
    "items": [
      {
        "nombre": "Escritorio Infantil",
        "cantidad": 1,
        "precio": "89.990",
        "imagen": "peque-mueble.webp"
      }
    ]
  }
]